lzy/__init__.py
lzy/lzy-servant.jar
lzy/_proxy/__init__.py
lzy/_proxy/automagic.py
lzy/_proxy/result.py
lzy/api/__init__.py
lzy/api/v1/__init__.py
lzy/api/v1/buses.py
lzy/api/v1/cache_policy.py
lzy/api/v1/env.py
lzy/api/v1/lazy_op.py
lzy/api/v1/signatures.py
lzy/api/v1/startup.py
lzy/api/v1/utils.py
lzy/api/v1/servant/__init__.py
lzy/api/v1/servant/bash_servant_client.py
lzy/api/v1/servant/channel_manager.py
lzy/api/v1/servant/servant_client.py
lzy/api/v1/servant/terminal_server.py
lzy/api/v1/servant/whiteboard_bash_api.py
lzy/api/v1/servant/whiteboard_storage.py
lzy/api/v1/servant/model/__init__.py
lzy/api/v1/servant/model/channel.py
lzy/api/v1/servant/model/encoding.py
lzy/api/v1/servant/model/env.py
lzy/api/v1/servant/model/execution.py
lzy/api/v1/servant/model/file_slots.py
lzy/api/v1/servant/model/return_codes.py
lzy/api/v1/servant/model/slot.py
lzy/api/v1/servant/model/zygote.py
lzy/api/v1/servant/model/zygote_python_func.py
lzy/api/v1/whiteboard/__init__.py
lzy/api/v1/whiteboard/model.py
lzy/api/v2/__init__.py
lzy/api/v2/utils.py
lzy/api/v2/api/local/__init__.py
lzy/api/v2/api/local/local_runtime.py
lzy/api/v2/api/local/local_snapshot.py
lzy/api/v2/api/local/local_snapshot_provider.py
lzy/api/v2/api/runtime/__init__.py
lzy/api/v2/api/runtime/runtime.py
lzy/api/v2/api/snapshot/__init__.py
lzy/api/v2/api/snapshot/snapshot.py
lzy/api/v2/api/snapshot/snapshot_provider.py
lzy/api/v2/servant/__init__.py
lzy/api/v2/servant/snapshot_api.py
lzy/api/v2/servant/terminal_server.py
lzy/api/v2/servant/whiteboard_api.py
lzy/api/v2/servant/model/__init__.py
lzy/api/v2/servant/model/channel.py
lzy/api/v2/servant/model/encoding.py
lzy/api/v2/servant/model/env.py
lzy/api/v2/servant/model/execution.py
lzy/api/v2/servant/model/file_slots.py
lzy/api/v2/servant/model/provisioning.py
lzy/api/v2/servant/model/return_codes.py
lzy/api/v2/servant/model/signatures.py
lzy/api/v2/servant/model/slot.py
lzy/api/v2/servant/model/zygote.py
lzy/api/v2/servant/model/zygote_python_func.py
pylzy_nightly-0.0.42.dist-info/METADATA
pylzy_nightly-0.0.42.dist-info/WHEEL
pylzy_nightly-0.0.42.dist-info/entry_points.txt
pylzy_nightly-0.0.42.dist-info/top_level.txt
pylzy_nightly-0.0.42.dist-info/RECORD
