Metadata-Version: 2.1
Name: pylzy-nightly
Version: 0.0.42.dev20220621
Summary: UNKNOWN
Author: ʎzy developers
License: UNKNOWN
Platform: UNKNOWN
Requires-Python: >=3.7
Requires-Dist: boto3 (>=1.20.24)
Requires-Dist: cloudpickle (>=2.0.0)
Requires-Dist: pyyaml (>=6.0)
Requires-Dist: importlib-metadata (>=4.8.1)
Requires-Dist: wheel (>=0.36.2)
Requires-Dist: azure-storage-blob (>=12.9.0)
Requires-Dist: requests (>=2.26)
Requires-Dist: stdlib-list (>=0.8.0)
Requires-Dist: hidden-pure-protobuf (>=0.2)
